Metadata-Version: 2.1
Name: pythonspinners
Version: 0.1.0a0
Summary: A simple package that provided loading screen objects for a passed function.
Author: Abhiram Mangipudi
Author-email: k0mplexontuta@tutamail.com
